poooli/__init__.py
poooli-0.1.4.dist-info/WHEEL
poooli-0.1.4.dist-info/METADATA
poooli-0.1.4.dist-info/RECORD
