Metadata-Version: 2.1
Name: poooli
Version: 0.1.4
Summary: A python library for printing on the Poooli thermal printer.
License: MIT
Author-email: Christoph Minixhofer <christoph.minixhofer@gmail.com>
Requires-Python: >=3.8
Requires-Dist: Pillow>=9.3.0
